blueblack/__init__.py
blueblack/config_loading.py
blueblack/local_logging.py
blueblack/main.py
blueblack/project.py
blueblack/script_runner.py
blueblack/states.py
blueblack/sun_times.py
blueblack/suntimes_fetcher.py
blueblack/transitions.py
blueblack-1.0.2.dist-info/METADATA
blueblack-1.0.2.dist-info/WHEEL
blueblack-1.0.2.dist-info/RECORD
