Metadata-Version: 2.1
Name: blueblack
Version: 1.0.2
Summary: Automatic light/dark mode transitions based on location
Author: Stefanos Mitropoulos
Requires-Python: >=3.12,<4.0
Classifier: Programming Language :: Python :: 3
Classifier: Programming Language :: Python :: 3.12
Requires-Dist: jsonschema (>=4.22.0,<5.0.0)
Requires-Dist: pyyaml (==6.0.1)
Requires-Dist: requests (==2.31.0)
Requires-Dist: xdg-base-dirs (==6.0.1)
